rasa_exporter
setup.py
DataGenerator/DataGenerator.py
DataGenerator/__init__.py
hd_training_exporter.egg-info/PKG-INFO
hd_training_exporter.egg-info/SOURCES.txt
hd_training_exporter.egg-info/dependency_links.txt
hd_training_exporter.egg-info/top_level.txt