Metadata-Version: 1.1
Name: hd-training-exporter
Version: 0.1
Summary: Generate Rasa training data from a csv file.
Home-page: UNKNOWN
Author: Harshit Daftary
Author-email: daftaryharshit@yahoo.co.in
License: UNKNOWN
Keywords: rasa ui,rasa,training,export
Platform: UNKNOWN
Classifier: Programming Language :: Python :: 3
Classifier: License :: OSI Approved :: MIT License
Classifier: Operating System :: OS Independent
